{
    "Numeus": 6,
    "total_jobs": 1254,
    "fireblocks": 84,
    "swanbitcoin": 2,
    "ninjatrader": 19,
    "nomina.io": 2,
    "recall": 2,
    "eiger": 1,
    "iftother": 8,
    "figure": 21,
    "wyndlabs": 11,
    "grayscaleinvestments": 12,
    "ssv.network": 2,
    "jumpcrypto": 6,
    "ritual": 15,
    "shardeum": 3,
    "orderlynetwork": 11,
    "zora": 2,
    "wormholefoundation": 8,
    "blockchain": 63,
    "bitmex": 25,
    "bitgo": 95,
    "OKX": 492,
    "bitpanda": 108,
    "figment": 2,
    "mara": 13,
    "xapo": 13,
    "exodus54": 4,
    "alchemy": 22,
    "magic": 2,
    "aztec": 2,
    "near": 1,
    "dfinity": 2,
    "bitcoindepot": 9,
    "taxbit": 11,
    "avalabs": 7,
    "aptoslabs": 4,
    "foundrydigital": 2,
    "strike.me": 6,
    "copperco": 8,
    "layerzerolabs": 20,
    "galaxydigital": 61,
    "brave": 12,
    "zetachain": 1,
    "noble": 3,
    "ramp.network": 2,
    "bvnk": 13,
    "meshpay": 27,
    "aPriori": 2,
    "cosmoslabs": 6,
    "messari": 1
}