{
    "Numeus": 6,
    "total_jobs": 799,
    "swanbitcoin": 2,
    "ninjatrader": 26,
    "nomina.io": 2,
    "recall": 2,
    "eiger": 1,
    "figure": 19,
    "iftother": 3,
    "wyndlabs": 11,
    "grayscaleinvestments": 6,
    "ssv.network": 1,
    "jumpcrypto": 7,
    "ritual": 15,
    "orderlynetwork": 10,
    "shardeum": 3,
    "zora": 2,
    "wormholefoundation": 3,
    "blockchain": 36,
    "bitmex": 22,
    "bitgo": 53,
    "OKX": 299,
    "bitpanda": 57,
    "figment": 1,
    "xapo": 19,
    "exodus54": 5,
    "near": 1,
    "bitcoindepot": 9,
    "taxbit": 9,
    "aptoslabs": 5,
    "immunefi": 2,
    "copperco": 5,
    "strike.me": 4,
    "galaxydigital": 60,
    "layerzerolabs": 18,
    "brave": 13,
    "noble": 1,
    "zetachain": 2,
    "ramp.network": 3,
    "bvnk": 22,
    "meshpay": 28,
    "aPriori": 2,
    "cosmoslabs": 3,
    "filecoinfoundation": 1
}