{
    "moonpay": 8,
    "total_jobs": 1404,
    "arbitrumfoundation": 9,
    "aragon": 2,
    "binance": 315,
    "blox-route": 5,
    "multiversx": 4,
    "sprucesystems": 4,
    "impossiblecloud": 17,
    "fuellabs": 2,
    "harmony": 9,
    "wintermute": 22,
    "coinspaid": 35,
    "kaiko": 2,
    "swissborg": 5,
    "ethereumfoundation": 6,
    "crypto": 471,
    "anchorage": 61,
    "centrifuge": 1,
    "tokenmetrics": 125,
    "offchainlabs": 18,
    "celestia": 1,
    "gauntlet": 12,
    "machinefilab": 0,
    "gate.io": 117,
    "auroralabs": 2,
    "immutable": 15,
    "cere-network": 4,
    "animocabrands": 32,
    "toku": 7,
    "coingecko": 15,
    "connext-network": 1,
    "ethenalabs": 11,
    "SeiLabs": 8,
    "theblock": 10,
    "bitwise": 7,
    "coinmarketcap": 15,
    "serotonin": 24,
    "Decentraland": 2
}