{
    "Total Jobs": 4738,
    "base": 13,
    "binance": 359,
    "lmax": 13,
    "kraken": 92,
    "lido": 6,
    "moonpay": 17,
    "phantom": 9,
    "obol-tech": 5,
    "arbitrumfoundation": 22,
    "chainlink": 80,
    "aragon": 1,
    "ondofinance": 17,
    "omni-network": 7,
    "Tenderly": 6,
    "injectivelabs": 10,
    "nomic.foundation": 6,
    "ethglobal": 3,
    "li.fi": 7,
    "Caldera": 8,
    "blox-route": 10,
    "multiversx": 32,
    "sprucesystems": 8,
    "BlockSwap": 2,
    "impossiblecloud": 11,
    "with-foundation": 2,
    "axiomzen": 5,
    "fuellabs": 15,
    "HQxyz": 6,
    "Notabene": 6,
    "harmony": 9,
    "wintermute": 15,
    "coinspaid": 30,
    "kaiko": 4,
    "bebop": 4,
    "Coinshift": 1,
    "swissborg": 17,
    "storyprotocol": 7,
    "ethereumfoundation": 6,
    "aave": 9,
    "crypto": 328,
    "Luxor": 1,
    "anchorage": 38,
    "biconomy": 4,
    "enso": 3,
    "Polygon": 7,
    "centrifuge": 3,
    "tokenmetrics": 428,
    "offchainlabs": 11,
    "subspacelabs": 2,
    "3boxlabs": 1,
    "ramp.network": 37,
    "eiger": 6,
    "risklabs": 8,
    "celestia": 3,
    "polymerlabs": 9,
    "swellnetwork": 2,
    "gauntlet": 9,
    "machinefilab": 21,
    "gate.io": 101,
    "auroralabs": 6,
    "ledger": 39,
    "immutable": 21,
    "web3auth": 5,
    "cere-network": 7,
    "matterlabs": 14,
    "monad": 11,
    "wyndlabs": 14,
    "expopulus": 10,
    "coinlist": 8,
    "animocabrands": 52,
    "toku": 19,
    "hiro": 5,
    "AQX": 22,
    "coingecko": 22,
    "emergentx": 1,
    "connext-network": 3,
    "ethenalabs": 3,
    "SeiLabs": 11,
    "theblock": 7,
    "bitwise": 1,
    "grayscaleinvestments": 13,
    "dydx": 9,
    "xlabs": 3,
    "movementlabs": 4,
    "0x": 5,
    "ritual": 7,
    "econetwork": 2,
    "magic": 2,
    "chainstack": 7,
    "outlierventures": 2,
    "coinmarketcap": 34,
    "evmos": 4,
    "pyth": 2,
    "orderlynetwork": 18,
    "shardeum": 5,
    "zora": 1,
    "blockchain": 31,
    "osl": 13,
    "cexio": 8,
    "circle": 451,
    "OKX": 349,
    "bitmex": 28,
    "bitgo": 55,
    "bitpanda": 61,
    "uniswaplabs": 15,
    "osmosisdex": 7,
    "penumbralabs": 2,
    "blockdaemon": 4,
    "figment": 7,
    "OpenSea": 3,
    "center": 6,
    "linera.io": 1,
    "shadow": 4,
    "cointracker": 10,
    "Bastion": 3,
    "Sui.Foundation": 9,
    "dourolabs": 6,
    "StationLabs": 2,
    "rain": 6,
    "mystenlabs": 11,
    "exponential": 4,
    "conduit": 7,
    "kiln": 12,
    "flashbots": 2,
    "paradigm.xyz": 11,
    "syndica": 16,
    "Blockworks": 6,
    "ellipsislabs": 7,
    "safe.global": 9,
    "cryptio": 12,
    "Artemisxyz": 2,
    "Boost": 2,
    "Keyrock": 10,
    "sound.xyz": 3,
    "quiknodeinc": 8,
    "21co": 9,
    "xapo": 8,
    "dragonflycapital": 18,
    "exodus54": 10,
    "alchemy": 15,
    "chainalysis": 48,
    "magiceden": 15,
    "aztec": 4,
    "near": 2,
    "nethermind": 38,
    "dfinity": 10,
    "stellar": 22,
    "parity": 6,
    "optimism": 6,
    "coinmetrics": 2,
    "oplabs": 11,
    "goldsky": 2,
    "walletconnect": 8,
    "prepo": 6,
    "io-global": 37,
    "clockwork-labs": 2,
    "o1labs": 7,
    "paradigm.co": 11,
    "trustwallet": 26,
    "Swissquote": 23,
    "taxbit": 14,
    "avalabs": 11,
    "aptoslabs": 34,
    "iyield": 1,
    "almanak": 4,
    "blast": 1,
    "windranger": 26,
    "filecoinfoundation": 1,
    "foundrydigital": 23,
    "immunefi": 4,
    "wirex": 10,
    "trmlabs": 16,
    "messari": 15,
    "copperco": 12,
    "digitalasset": 2,
    "layerzerolabs": 11,
    "oasisnetwork": 15,
    "ankr": 1,
    "chainsafesystems": 7,
    "ripple": 65,
    "eigenlabs": 10,
    "sygnum": 15,
    "galaxydigitalservices": 45,
    "web3": 2,
    "worldcoin": 78,
    "edgeandnode": 11,
    "clearmatics": 6,
    "yugalabs": 2,
    "brave": 6,
    "bitstamp": 6,
    "tatum": 4,
    "cryptofinance": 7,
    "hextrust": 17,
    "zodia-custody": 6,
    "paraswap": 2,
    "stakefish": 6,
    "thetie": 9,
    "tusd": 2,
    "status": 11,
    "gemini": 90,
    "tether": 10,
    "mina-foundation": 6,
    "consensys": 31,
    "coinbase": 233
}