{
    "total_jobs": 1063,
    "trading212": 39,
    "truelayer": 6,
    "flex": 71,
    "atticus.com": 13,
    "Aven": 6,
    "Ivy": 7,
    "qonto": 45,
    "moneybox": 16,
    "interactivebrokers": 148,
    "affirm": 158,
    "9fin": 49,
    "grape-health": 9,
    "cmgx": 6,
    "addepar": 86,
    "capitalontap": 43,
    "clearstreet": 33,
    "onepay.com": 26,
    "swingdev": 6,
    "yuno": 17,
    "capital": 54,
    "smartasset": 8,
    "earnin": 56,
    "rillet.com": 27,
    "getrecharge.com": 6,
    "Cleo": 67,
    "huspy": 61
}