{
    "data": [
        {
            "company": "trading212",
            "title": "Junior Compliance Analyst",
            "location": "Sydney",
            "link": "https://jobs.ashbyhq.com/trading212/18b8afcd-ed36-4c07-b0d7-fb7f40c03f6c"
        },
        {
            "company": "trading212",
            "title": "Junior Operations Analyst",
            "location": "Sydney",
            "link": "https://jobs.ashbyhq.com/trading212/fd75145a-5c56-499b-86fa-1e2f973c1f98"
        },
        {
            "company": "trading212",
            "title": "Junior Risk Analyst",
            "location": "Sydney",
            "link": "https://jobs.ashbyhq.com/trading212/022d6438-dda8-46a1-ae21-5b6ab12735c3"
        },
        {
            "company": "interactivebrokers",
            "title": "Analyst - ClearingNew",
            "location": "Hong Kong",
            "link": "https://job-boards.greenhouse.io/ibkr/jobs/8534162002"
        },
        {
            "company": "interactivebrokers",
            "title": "Financial Services AssociateNew",
            "location": "Vancouver, BC, Canada",
            "link": "https://job-boards.greenhouse.io/ibkr/jobs/8534759002"
        },
        {
            "company": "interactivebrokers",
            "title": "FIU AnalystNew",
            "location": "Hong Kong",
            "link": "https://job-boards.greenhouse.io/ibkr/jobs/8527725002"
        },
        {
            "company": "interactivebrokers",
            "title": "Senior Manager, Media Optimization",
            "location": "Greenwich, CT",
            "link": "https://job-boards.greenhouse.io/ibkr/jobs/8366573002"
        },
        {
            "company": "flex",
            "title": "Senior Director, Strategic PartnershipsNew",
            "location": "New York, New York, US",
            "link": "https://job-boards.greenhouse.io/flex/jobs/4692932005"
        },
        {
            "company": "flex",
            "title": "Senior Director, Strategic PartnershipsNew",
            "location": "San Francisco, California, US",
            "link": "https://job-boards.greenhouse.io/flex/jobs/4692940005"
        },
        {
            "company": "flex",
            "title": "Senior Director, Strategy & Operations (Housing)New",
            "location": "New York, New York, US",
            "link": "https://job-boards.greenhouse.io/flex/jobs/4693114005"
        },
        {
            "company": "flex",
            "title": "Senior Manager, Strategic FinanceNew",
            "location": "New York, New York, US",
            "link": "https://job-boards.greenhouse.io/flex/jobs/4692907005"
        },
        {
            "company": "flex",
            "title": "Senior Manager, Strategic FinanceNew",
            "location": "San Francisco, California, US",
            "link": "https://job-boards.greenhouse.io/flex/jobs/4692908005"
        },
        {
            "company": "flex",
            "title": "Associate General Counsel, Product & RegulatoryNew",
            "location": "San Francisco, California, US",
            "link": "https://job-boards.greenhouse.io/flex/jobs/4692206005"
        },
        {
            "company": "flex",
            "title": "Director, New Verticals Sales (Auto Loans)New",
            "location": "New York, New York, US; Remote (U.S.); San Francisco, California, US",
            "link": "https://job-boards.greenhouse.io/flex/jobs/4692155005"
        },
        {
            "company": "flex",
            "title": "Senior Director, New Verticals Sales (Insurance)New",
            "location": "New York, New York, US; Remote (U.S.); San Francisco, California, US",
            "link": "https://job-boards.greenhouse.io/flex/jobs/4692132005"
        },
        {
            "company": "flex",
            "title": "Vice President of Sales, New VerticalsNew",
            "location": "New York, New York, US; Salt Lake City, Utah, US; San Francisco, California, US",
            "link": "https://job-boards.greenhouse.io/flex/jobs/4687391005"
        },
        {
            "company": "flex",
            "title": "VP of Account Management, New VerticalsNew",
            "location": "New York, New York, US; Salt Lake City, Utah, US; San Francisco, California, US",
            "link": "https://job-boards.greenhouse.io/flex/jobs/4692301005"
        },
        {
            "company": "flex",
            "title": "VP of Account Management, Core HousingNew",
            "location": "New York, New York, US",
            "link": "https://job-boards.greenhouse.io/flex/jobs/4692695005"
        },
        {
            "company": "flex",
            "title": "GTM Strategy & Operations AssociateNew",
            "location": "New York, New York, US",
            "link": "https://job-boards.greenhouse.io/flex/jobs/4692266005"
        },
        {
            "company": "flex",
            "title": "Senior Manager, Revenue EnablementNew",
            "location": "New York, New York, US; Salt Lake City, Utah, US; San Francisco, California, US",
            "link": "https://job-boards.greenhouse.io/flex/jobs/4692186005"
        },
        {
            "company": "flex",
            "title": "Senior Manager, Revenue EnablementNew",
            "location": "San Francisco, California, US",
            "link": "https://job-boards.greenhouse.io/flex/jobs/4692192005"
        },
        {
            "company": "flex",
            "title": "Senior Manager, Revenue EnablementNew",
            "location": "Salt Lake City, Utah, US",
            "link": "https://job-boards.greenhouse.io/flex/jobs/4692197005"
        },
        {
            "company": "qonto",
            "title": "Accounts Payable (Fixed-Term Contract - 9 months starting June 2026)",
            "location": "PARIS / BELGRADE,HYBRID",
            "link": "https://jobs.lever.co/qonto/5012cda2-458b-495e-a041-d95ab718309e"
        },
        {
            "company": "qonto",
            "title": "Senior/Staff - Backend Engineer - remote friendly",
            "location": "BERLIN,REMOTE",
            "link": "https://jobs.lever.co/qonto/a2a71652-40f6-4c1a-8ae1-90127e0ce1cf"
        },
        {
            "company": "qonto",
            "title": "Senior/Staff - Backend Engineer - remote friendly",
            "location": "BARCELONA,REMOTE",
            "link": "https://jobs.lever.co/qonto/1fb7a10a-9377-47d4-99f6-e826880c3a6b"
        },
        {
            "company": "qonto",
            "title": "Senior iOS Engineer",
            "location": "MILAN,REMOTE",
            "link": "https://jobs.lever.co/qonto/7d508564-98c1-4cca-8633-dc8e87b7fd79"
        },
        {
            "company": "qonto",
            "title": "Software Engineer (Engineering Efficiency) - remote friendly",
            "location": "PARIS / BERLIN / BARCELONA / MILAN / BELGRADE,HYBRID",
            "link": "https://jobs.lever.co/qonto/1f945bad-2c45-4ac1-be06-a219dc9e1a93"
        },
        {
            "company": "qonto",
            "title": "Staff SAP Engineer",
            "location": "PARIS / BARCELONA / BERLIN / MILAN / BELGRADE,REMOTE",
            "link": "https://jobs.lever.co/qonto/9df8691c-1c3a-4ec4-9d58-2ef220f1b502"
        },
        {
            "company": "affirm",
            "title": "Strategic Finance Analyst II (Revenue)New",
            "location": "Remote US",
            "link": "https://job-boards.greenhouse.io/affirm/jobs/7724227003"
        },
        {
            "company": "affirm",
            "title": "Strategic Finance Analyst II (Revenue)New",
            "location": "Remote Canada",
            "link": "https://job-boards.greenhouse.io/affirm/jobs/7724229003"
        },
        {
            "company": "affirm",
            "title": "Director, Partner MarketingNew",
            "location": "Remote US",
            "link": "https://job-boards.greenhouse.io/affirm/jobs/7721123003"
        },
        {
            "company": "affirm",
            "title": "Director of Product Management, Financial PlatformsNew",
            "location": "Remote US",
            "link": "https://job-boards.greenhouse.io/affirm/jobs/7718659003"
        },
        {
            "company": "affirm",
            "title": "Director of Product Management, Financial PlatformsNew",
            "location": "Remote Canada",
            "link": "https://job-boards.greenhouse.io/affirm/jobs/7718661003"
        },
        {
            "company": "affirm",
            "title": "Business Systems Analyst IINew",
            "location": "Remote Canada",
            "link": "https://job-boards.greenhouse.io/affirm/jobs/7721457003"
        },
        {
            "company": "affirm",
            "title": "Business Systems Analyst IINew",
            "location": "Remote US",
            "link": "https://job-boards.greenhouse.io/affirm/jobs/7721455003"
        },
        {
            "company": "9fin",
            "title": "Investment Grade Reporter",
            "location": "London",
            "link": "https://jobs.ashbyhq.com/9fin/1b60b6c8-25f5-4d16-9bfd-2bfdef2ae945"
        },
        {
            "company": "grape-health",
            "title": "Account Executive",
            "location": "Z\u00dcRICH,HYBRID",
            "link": "https://jobs.eu.lever.co/grape-health/77949b79-adf4-43ea-bea9-a1c0e255ab1a"
        },
        {
            "company": "grape-health",
            "title": "Product Support Manager",
            "location": "Z\u00dcRICH,HYBRID",
            "link": "https://jobs.eu.lever.co/grape-health/a5008b2c-c85a-4986-8e2e-e6575ecc768e"
        },
        {
            "company": "addepar",
            "title": "Associate Portfolio Data AnalystNew",
            "location": "Pune, India",
            "link": "https://job-boards.greenhouse.io/addepar1/jobs/8532487002"
        },
        {
            "company": "addepar",
            "title": "Staff Backend Software Engineer - Portfolio Data WorkflowNew",
            "location": "Poland",
            "link": "https://job-boards.greenhouse.io/addepar1/jobs/8511219002"
        },
        {
            "company": "addepar",
            "title": "Data EngineerNew",
            "location": "Edinburgh, UK",
            "link": "https://job-boards.greenhouse.io/addepar1/jobs/8515929002"
        },
        {
            "company": "addepar",
            "title": "Junior Software Engineer - Data Intelligence (ADX)New",
            "location": "Edinburgh, UK",
            "link": "https://job-boards.greenhouse.io/addepar1/jobs/8535085002"
        },
        {
            "company": "addepar",
            "title": "Product AnalystNew",
            "location": "Edinburgh, UK",
            "link": "https://job-boards.greenhouse.io/addepar1/jobs/8529887002"
        },
        {
            "company": "addepar",
            "title": "Product Manager - Data IntelligenceNew",
            "location": "Edinburgh, UK",
            "link": "https://job-boards.greenhouse.io/addepar1/jobs/8535082002"
        },
        {
            "company": "addepar",
            "title": "Staff Product ManagerNew",
            "location": "Edinburgh, UK",
            "link": "https://job-boards.greenhouse.io/addepar1/jobs/8532390002"
        },
        {
            "company": "capitalontap",
            "title": "Credit UnderwriterNew",
            "location": "London",
            "link": "https://job-boards.greenhouse.io/capitalontap/jobs/8536267002"
        },
        {
            "company": "capitalontap",
            "title": "Financial Crime Compliance Analyst",
            "location": "New York",
            "link": "https://job-boards.greenhouse.io/capitalontap/jobs/8455462002"
        },
        {
            "company": "onepay.com",
            "title": "Design Engineer",
            "location": "US (Remote)",
            "link": "https://jobs.ashbyhq.com/oneapp/b7ae2b9b-0f31-468d-9ac8-395536da8beb"
        },
        {
            "company": "onepay.com",
            "title": "Design Systems Engineer",
            "location": "US (Remote)",
            "link": "https://jobs.ashbyhq.com/oneapp/ce0659c0-aae0-48a9-874d-27d65e1092ca"
        },
        {
            "company": "onepay.com",
            "title": "Finance",
            "location": "US (Remote)",
            "link": "https://jobs.ashbyhq.com/oneapp/31ccddd8-a1c4-4e02-9716-94dbef4ca608"
        },
        {
            "company": "yuno",
            "title": "Solutions Engineer - Financial Institutions",
            "location": "EUROPE / ITALY / PORTUGAL,REMOTE",
            "link": "https://jobs.lever.co/yuno/3a2a1909-b04f-4016-b8eb-0b10ffdcefb0"
        },
        {
            "company": "yuno",
            "title": "Payments Operations Analyst",
            "location": "HYDERABAD,ON-SITE",
            "link": "https://jobs.lever.co/yuno/aec1c95b-3e33-4327-808d-93060286ccfa"
        },
        {
            "company": "yuno",
            "title": "Product Designer",
            "location": "BOGOTA / BUENOS AIRES / ARGENTINA / CHILE / MEXICO / COLOMBIA / ECUADOR / DOMINICAN REPUBLIC / LIMA / PARAGUAY / PUERTO RICO / S\u00c3O PAULO / SPAIN / PORTUGAL,REMOTE",
            "link": "https://jobs.lever.co/yuno/629673a2-c969-4c1b-8dbf-8e8be7bb455b"
        },
        {
            "company": "yuno",
            "title": "Strategy & Operations Manager",
            "location": "HYDERABAD,ON-SITE",
            "link": "https://jobs.lever.co/yuno/27229bcf-fbf1-4eb6-b1d2-15dfd1b5569c"
        },
        {
            "company": "capital",
            "title": "Outsourcing & Third-Party Risk Manager",
            "location": "WARSAW, MAZOWIECKIE, POLAND / DUBAI / SOFIA CITY, BULGARIA / LIMASSOL, CYPRUS,HYBRID",
            "link": "https://jobs.lever.co/capital/4a5131c5-dea7-4a43-87b3-11c4e8d503b7"
        },
        {
            "company": "capital",
            "title": "Group Compliance Assurance Testing Manager",
            "location": "LONDON, ENGLAND, UK,HYBRID",
            "link": "https://jobs.lever.co/capital/45801ce2-8bcc-4651-8be3-808fb18c3c94"
        },
        {
            "company": "capital",
            "title": "Senior Legal Counsel (Payments, PSPs & EMIs)",
            "location": "LIMASSOL, CYPRUS,HYBRID",
            "link": "https://jobs.lever.co/capital/b07a6f65-dbcd-4b3d-b02d-dfdbadae0157"
        },
        {
            "company": "capital",
            "title": "Legal Counsel",
            "location": "WARSAW, MAZOWIECKIE, POLAND / SOFIA CITY, BULGARIA / LIMASSOL, CYPRUS,HYBRID",
            "link": "https://jobs.lever.co/capital/b5ef923b-b0d6-4331-81ec-979d054d1856"
        },
        {
            "company": "capital",
            "title": "Marketing Manager Germany",
            "location": "FRANKFURT AM MAIN, HESSE,HYBRID",
            "link": "https://jobs.lever.co/capital/764d347a-9fa5-4643-b509-b9c61e778d1f"
        },
        {
            "company": "capital",
            "title": "Back Office Officer (On-Boarding)",
            "location": "MELBOURNE, VICTORIA, AUSTRALIA,HYBRID",
            "link": "https://jobs.lever.co/capital/9c7baaff-ba48-4991-b09e-5ac1c785eeb0"
        },
        {
            "company": "capital",
            "title": "Senior Security Operations Center Analyst",
            "location": "LIMASSOL, CYPRUS,HYBRID",
            "link": "https://jobs.lever.co/capital/e88053b6-786d-4714-8dd7-ce1030a57db3"
        },
        {
            "company": "capital",
            "title": "Junior Trader",
            "location": "LIMASSOL, CYPRUS,ON-SITE",
            "link": "https://jobs.lever.co/capital/eb168fa2-4b3b-4bea-9d49-e8c44cea59d1"
        },
        {
            "company": "smartasset",
            "title": "Director, AccountingNew",
            "location": "Remote",
            "link": "https://job-boards.greenhouse.io/smartasset/jobs/8508443002"
        },
        {
            "company": "earnin",
            "title": "Risk Data AnalystNew",
            "location": "Bengaluru, India",
            "link": "https://job-boards.greenhouse.io/earnin/jobs/7874503"
        },
        {
            "company": "earnin",
            "title": "Senior Full Stack EngineerNew",
            "location": "Mountain View, US",
            "link": "https://job-boards.greenhouse.io/earnin/jobs/7886143"
        },
        {
            "company": "earnin",
            "title": "Software EngineerNew",
            "location": "Bengaluru, India",
            "link": "https://job-boards.greenhouse.io/earnin/jobs/7874840"
        },
        {
            "company": "earnin",
            "title": "Product Operations SpecialistNew",
            "location": "Mountain View, US",
            "link": "https://job-boards.greenhouse.io/earnin/jobs/7895725"
        },
        {
            "company": "rillet.com",
            "title": "Deployment Lead - ERP Solutions",
            "location": "Remote; New York City; San Francisco",
            "link": "https://jobs.ashbyhq.com/rillet/27d6e823-4edb-435d-a0f0-45efabbcad15"
        },
        {
            "company": "Cleo",
            "title": "Senior Product Performance Associate",
            "location": "Office: UK",
            "link": "https://revolutpeople.com/cleo/public/careers/position/senior-product-performance-associate-3dd5cc7f-2d28-476b-98a6-08e5f407a0c3"
        },
        {
            "company": "Cleo",
            "title": "Social Media - Influencer Manager",
            "location": "Remote: US",
            "link": "https://revolutpeople.com/cleo/public/careers/position/social-media-influencer-manager-d0060af6-5cec-4065-889b-f4045e764ee9"
        },
        {
            "company": "Cleo",
            "title": "Head of Fraud",
            "location": "Remote: UK | US",
            "link": "https://revolutpeople.com/cleo/public/careers/position/head-of-fraud-02671591-342f-4910-92e3-90ef448c474c"
        },
        {
            "company": "huspy",
            "title": "Product Designer",
            "location": "Remote: Armenia | Austria | Bosnia and Herzegovina | Cyprus | Czech Republic | Estonia | Finland | Georgia +11",
            "link": "https://revolutpeople.com/huspy/public/careers/position/product-designer-52c99ec9-50d5-490e-a19b-6a69a4915372"
        },
        {
            "company": "huspy",
            "title": "Data Scientist",
            "location": "Remote: Armenia | Austria | Bosnia and Herzegovina | Cyprus | Czech Republic | Estonia | Finland | Georgia +9",
            "link": "https://revolutpeople.com/huspy/public/careers/position/data-scientist-1413a2ef-674f-4684-8a6a-77c8f3a8c214"
        },
        {
            "company": "huspy",
            "title": "Operations Manager",
            "location": "Office: Barcelona | Madrid | Milan",
            "link": "https://revolutpeople.com/huspy/public/careers/position/operations-manager-0c92f816-f331-4010-92ec-8d4b909d5ffe"
        },
        {
            "company": "huspy",
            "title": "Office Manager - Alicante",
            "location": "Office: Alicante",
            "link": "https://revolutpeople.com/huspy/public/careers/position/office-manager-alicante-4d6cd555-502b-45fe-ba09-e2f649ad3b7c"
        },
        {
            "company": "huspy",
            "title": "Head of Agent Lifecycle (CEO Office)",
            "location": "Office: Madrid | Milan",
            "link": "https://revolutpeople.com/huspy/public/careers/position/head-of-agent-lifecycle-ceo-office-7ff77da0-f2f3-41bc-a88e-71239ab23bce"
        }
    ]
}