{
    "data": [
        {
            "company": "chainlink",
            "title": "Growth Manager, RWA",
            "location": "\u2014 Amsterdam / Remote / Ciudad De M\u00e9xico / Remote / Singapore / Remote",
            "link": "<a href='https://jobs.lever.co/chainlink/80f649cc-63a4-4d9c-90ef-133eea456d48' target='_blank' >Apply</a>"
        },
        {
            "company": "toku",
            "title": "Director of Token Payroll",
            "location": "United States Remote",
            "link": "<a href='https://jobs.lever.co/toku/07202088-3cd2-41f9-89a9-c6754d4e987c' target='_blank' >Apply</a>"
        },
        {
            "company": "grayscaleinvestments",
            "title": "Art Director",
            "location": "Connecticut Stamford United States",
            "link": "<a href='https://boards.greenhouse.io/grayscaleinvestments/jobs/5829248003' target='_blank' >Apply</a>"
        },
        {
            "company": "dydx",
            "title": "Lead Technical Writer",
            "location": "New York Ny",
            "link": "<a href='https://boards.greenhouse.io/dydx/jobs/7057976002' target='_blank' >Apply</a>"
        },
        {
            "company": "OKX",
            "title": "Community Manager, OKX Argentina",
            "location": "Argentina (Remote)",
            "link": "<a href='https://boards.greenhouse.io/okx/jobs/5829222003' target='_blank' >Apply</a>"
        },
        {
            "company": "quiknodeinc",
            "title": "Marketing Operations Manager",
            "location": "Remote",
            "link": "<a href='https://boards.greenhouse.io/quiknodeinc/jobs/4312667006' target='_blank' >Apply</a>"
        },
        {
            "company": "chainalysis",
            "title": "Platform Engineer",
            "location": "Canada",
            "link": "<a href='https://jobs.ashbyhq.com/chainalysis-careers/85fe21a3-51e7-48bf-854e-d13e8ed56491' target='_blank' >Apply</a>"
        },
        {
            "company": "optimism",
            "title": "Product Marketing Manager",
            "location": "Remote",
            "link": "<a href='https://boards.greenhouse.io/optimism/jobs/5035729004' target='_blank' >Apply</a>"
        },
        {
            "company": "optimism",
            "title": "Social Manager",
            "location": "Remote",
            "link": "<a href='https://boards.greenhouse.io/optimism/jobs/5035732004' target='_blank' >Apply</a>"
        },
        {
            "company": "avalabs",
            "title": "Community Manager, Gaming",
            "location": "Ny Or Remote (Usa) New York",
            "link": "<a href='https://boards.greenhouse.io/avalabs/jobs/5024206004' target='_blank' >Apply</a>"
        },
        {
            "company": "foundrydigital",
            "title": "Mechanical / Industrial Engineering - Intern (Spring Semester)",
            "location": "Rochester Ny",
            "link": "<a href='https://boards.greenhouse.io/foundrydigital/jobs/5035891004' target='_blank' >Apply</a>"
        },
        {
            "company": "trmlabs",
            "title": "Product Marketing Manager - Public Sector",
            "location": "Remote",
            "link": "<a href='https://www.trmlabs.com/careers-list?gh_jid=5036362004' target='_blank' >Apply</a>"
        },
        {
            "company": "kadena",
            "title": "Frontend UI Component Developer",
            "location": "Remote",
            "link": "<a href='https://boards.greenhouse.io/kadenallc/jobs/4348499005' target='_blank' >Apply</a>"
        },
        {
            "company": "coinbase",
            "title": "Head of Technical Accounting Policy",
            "location": "Remote - USA",
            "link": "<a href='https://www.coinbase.com/careers/positions/5557558' target='_blank' >Apply</a>"
        }
    ]
}