{
    "data": [
        {
            "company": "binance",
            "title": "Partnership Manager - Latam",
            "location": "Colombia Bogota  Onsite or Remote",
            "link": "<a href='https://www.binance.com/en/careers/job?id=3e823ecc-5903-4a02-aa2f-1ffac51fbcb5' target='_blank' >Apply</a>"
        },
        {
            "company": "binance",
            "title": "Earn Operation and User Growth",
            "location": "Asia  Onsite or Remote",
            "link": "<a href='https://www.binance.com/en/careers/job?id=8d8ad328-049a-461b-895a-eab30180cf0f' target='_blank' >Apply</a>"
        },
        {
            "company": "kraken",
            "title": "DevOps - CF Benchmarks",
            "location": "Europe - Remote, Ireland - Remote, United Kingdom - Remote",
            "link": "<a href='https://jobs.ashbyhq.com/kraken.com/f40923d9-4fbd-46b5-b7f4-0e579b587692' target='_blank' >Apply</a>"
        },
        {
            "company": "moonpay",
            "title": "Product Manager, Consumer",
            "location": "4 Locations",
            "link": "<a href='https://moonpay.wd1.myworkdayjobs.com/en-US/GTI/job/London-United-Kingdom/Product-Manager--Consumer_JR100079' target='_blank' >Apply</a>"
        },
        {
            "company": "crypto",
            "title": "HR Manager, Operations / HRBP , Bulgaria",
            "location": "On-Site  Bulgaria Sofia",
            "link": "<a href='https://jobs.lever.co/crypto/118fad90-c9f9-4aa8-a6f7-238665670eb1' target='_blank' >Apply</a>"
        },
        {
            "company": "ramp.network",
            "title": "Compliance Manager",
            "location": "London United Kingdom England",
            "link": "<a href='https://boards.eu.greenhouse.io/rampnetwork/jobs/4275430101' target='_blank' >Apply</a>"
        },
        {
            "company": "gate.io",
            "title": "Customer QA Specialist",
            "location": "Apac Remote",
            "link": "<a href='https://jobs.lever.co/gate.io/638b0321-b855-40c4-bc29-3e9db31e6e13' target='_blank' >Apply</a>"
        },
        {
            "company": "ledger",
            "title": "Backend Software Engineer - Internship",
            "location": "On-Site  France Paris",
            "link": "<a href='https://jobs.lever.co/ledger/cc7dd9a8-315c-4b2b-8df8-a91d8451b07b' target='_blank' >Apply</a>"
        },
        {
            "company": "OKX",
            "title": "Engineering Manager - Java (Exchange Platform - Trading Services)",
            "location": "Singapore",
            "link": "<a href='https://boards.greenhouse.io/okx/jobs/5858689003' target='_blank' >Apply</a>"
        },
        {
            "company": "OKX",
            "title": "Principal Engineer/Staff Engineer - Container Development Engineer",
            "location": "Hong Kong",
            "link": "<a href='https://boards.greenhouse.io/okx/jobs/5857148003' target='_blank' >Apply</a>"
        },
        {
            "company": "OKX",
            "title": "Senior Software Engineer - OKEngine",
            "location": "Singapore",
            "link": "<a href='https://boards.greenhouse.io/okx/jobs/5858660003' target='_blank' >Apply</a>"
        },
        {
            "company": "OKX",
            "title": "Senior Product Manager, Blockchain Explorer",
            "location": "Singapore",
            "link": "<a href='https://boards.greenhouse.io/okx/jobs/5858679003' target='_blank' >Apply</a>"
        },
        {
            "company": "OKX",
            "title": "Senior Product Manager - Trading Service",
            "location": "Hong Kong",
            "link": "<a href='https://boards.greenhouse.io/okx/jobs/5858841003' target='_blank' >Apply</a>"
        },
        {
            "company": "paradigm.co",
            "title": "Head of Product Marketing",
            "location": "Singapore",
            "link": "<a href='https://boards.greenhouse.io/paradigm62/jobs/5058086004' target='_blank' >Apply</a>"
        },
        {
            "company": "dune",
            "title": "Product Designer",
            "location": "Europe And Us Based",
            "link": "<a href='https://jobs.ashbyhq.com/dune/297f4714-ed30-4c91-b759-ccd7058adacb' target='_blank' >Apply</a>"
        },
        {
            "company": "sygnum",
            "title": "Intern - Product & Platform Management Custody & DeFi",
            "location": "Hybrid Zh (Hybrid) Zurich",
            "link": "<a href='https://sygnum.bamboohr.com/careers/100' target='_blank' >Apply</a>"
        },
        {
            "company": "bitstamp",
            "title": "Pricing, Liquidity and Markets Manager",
            "location": "Hybrid",
            "link": "<a href='https://apply.workable.com/bitstamp/j/03F87D0006/' target='_blank' >Apply</a>"
        },
        {
            "company": "bitstamp",
            "title": "Pricing, Liquidity and Markets Manager",
            "location": "Hybrid",
            "link": "<a href='https://apply.workable.com/bitstamp/j/3C452B621A/' target='_blank' >Apply</a>"
        },
        {
            "company": "hextrust",
            "title": "Junior Accountant",
            "location": "Remote",
            "link": "<a href='https://apply.workable.com/hextrust/j/5D3EAED9F5/' target='_blank' >Apply</a>"
        },
        {
            "company": "coinbase",
            "title": "Associate, Growth, Payments & Platform Business Development",
            "location": "Remote - UK",
            "link": "<a href='https://www.coinbase.com/careers/positions/5616203' target='_blank' >Apply</a>"
        },
        {
            "company": "coinbase",
            "title": "Director, Head of Consumer Business Development",
            "location": "Remote - USA",
            "link": "<a href='https://www.coinbase.com/careers/positions/5613227' target='_blank' >Apply</a>"
        }
    ]
}